bedrock_ge/__init__.py
bedrock_ge/plot.py
bedrock_ge/gi/__init__.py
bedrock_ge/gi/ags.py
bedrock_ge/gi/ags3.py
bedrock_ge/gi/ags3_data_dictionary.json
bedrock_ge/gi/ags4.py
bedrock_ge/gi/ags4_data_dictionary.json
bedrock_ge/gi/ags_schemas.py
bedrock_ge/gi/db_operations.py
bedrock_ge/gi/geospatial.py
bedrock_ge/gi/io_utils.py
bedrock_ge/gi/mapper.py
bedrock_ge/gi/mapping_models.py
bedrock_ge/gi/schemas.py
bedrock_ge/gi/sqlmodels.py
bedrock_ge/gi/validate.py
bedrock_ge/gi/write.py
bedrock_ge-0.3.3.dist-info/METADATA
bedrock_ge-0.3.3.dist-info/WHEEL
bedrock_ge-0.3.3.dist-info/licenses/LICENSE
bedrock_ge-0.3.3.dist-info/RECORD
