Metadata-Version: 2.4
Name: bedrock-ge
Version: 0.3.3
Summary: Bedrock's Python library for geotechnical engineering.
Project-URL: Homepage, https://bedrock.engineer/
Project-URL: Source, https://github.com/bedrock-engineer/bedrock-ge
Project-URL: Documentation, https://bedrock.engineer/docs/
Project-URL: Tracker, https://github.com/bedrock-engineer/bedrock-ge/issues
Author-email: Bedrock <info@bedrock.engineer>
License: Apache Software License (Apache 2.0)
License-File: LICENSE
Keywords: aec,aeco,ags,ags3,ags4,bedrock,bim,borehole,borehole-data,civil-engineering,engineering-geology,geo-bim,geoscience-bim,geosciences,geospatial,geospatial-data,geostatistics,geotech,geotechnical,geotechnical-data,geotechnical-engineering,geotechnics,gi-data,gis,ground-engineering,ground-investigation,ground-investigation-data,subsurface,underground
Classifier: Development Status :: 3 - Alpha
Classifier: Intended Audience :: Education
Classifier: Intended Audience :: Science/Research
Classifier: License :: OSI Approved :: Apache Software License
Classifier: Operating System :: OS Independent
Classifier: Programming Language :: Python
Classifier: Programming Language :: Python :: 3 :: Only
Classifier: Programming Language :: Python :: 3.10
Classifier: Programming Language :: Python :: 3.11
Classifier: Programming Language :: Python :: 3.12
Classifier: Programming Language :: Python :: 3.13
Classifier: Topic :: Scientific/Engineering
Classifier: Topic :: Scientific/Engineering :: GIS
Requires-Python: >=3.10
Requires-Dist: chardet>=5.2.0
Requires-Dist: geopandas~=1.0
Requires-Dist: openpyxl~=3.0
Requires-Dist: pandera>=0.23.0
Requires-Dist: python-ags4~=1.0
Requires-Dist: sqlmodel>=0.0.22
